upref/__init__.py
upref/core.py
upref/default.conf
upref/gui.py
upref/tower.ico
upref/tty.py
upref/version.py
upref-1.0.14.dist-info/LICENSE.md
upref-1.0.14.dist-info/METADATA
upref-1.0.14.dist-info/WHEEL
upref-1.0.14.dist-info/top_level.txt
upref-1.0.14.dist-info/RECORD
