Metadata-Version: 2.1
Name: upref
Version: 1.0.14
Summary: UNKNOWN
Home-page: https://github.com/IIXIXII/upref
Author: Florent Tournois
Author-email: florent.tournois@gmail.fr
License: MIT
Platform: UNKNOWN
Classifier: Programming Language :: Python
Classifier: Operating System :: OS Independent
Classifier: Programming Language :: Python :: 3
Classifier: Programming Language :: Python :: 3.5
Requires-Dist: pyyaml
Requires-Dist: appdirs
